{
  "forge_marker": 1,
  "defaults": {
    "textures": {
      "particle": "blocks/hopper_outside",
      "all": "blocks/hopper_outside"
    },
    "model": "lightningadditions:tube_center",
    "uvlock": true
  },
  "variants": {
    "flow": {
      "updown": {
        "submodel": {
          "input": {
            "model": "lightningadditions:tube_top_input"
          },
          "output": {
            "model": "lightningadditions:tube_bottom_output"
          }
        }
      },
      "northdown": {
        "submodel": {
          "input": {
            "model": "lightningadditions:tube_horizontal_input",
            "y": 180
          },
          "output": {
            "model": "lightningadditions:tube_bottom_output"
          }
        }
      },
      "southdown": {
        "submodel": {
          "input": {
            "model": "lightningadditions:tube_horizontal_input"
          },
          "output": {
            "model": "lightningadditions:tube_bottom_output"
          }
        }
      },
      "northup": {
        "submodel": {
          "input": {
            "model": "lightningadditions:tube_horizontal_input",
            "y": 180
          },
          "output": {
            "model": "lightningadditions:tube_top_output"
          }
        }
      },
      "southup": {
        "submodel": {
          "input": {
            "model": "lightningadditions:tube_horizontal_input"
          },
          "output": {
            "model": "lightningadditions:tube_top_output"
          }
        }
      },
      "southnorth": {
        "submodel": {
          "input": {
            "model": "lightningadditions:tube_horizontal_input"
          },
          "output": {
            "model": "lightningadditions:tube_horizontal_output"
          }
        }
      },
      "westnorth": {
        "submodel": {
          "input": {
            "model": "lightningadditions:tube_horizontal_input",
            "y": 90
          },
          "output": {
            "model": "lightningadditions:tube_horizontal_output"
          }
        }
      },
      "eastnorth": {
        "submodel": {
          "input": {
            "model": "lightningadditions:tube_horizontal_input",
            "y": 270
          },
          "output": {
            "model": "lightningadditions:tube_horizontal_output"
          }
        }
      },
      "westsouth": {
        "submodel": {
          "input": {
            "model": "lightningadditions:tube_horizontal_input",
            "y": 90
          },
          "output": {
            "model": "lightningadditions:tube_horizontal_output",
            "y": 180
          }
        }
      },
      "eastsouth": {
        "submodel": {
          "input": {
            "model": "lightningadditions:tube_horizontal_input",
            "y": 270
          },
          "output": {
            "model": "lightningadditions:tube_horizontal_output",
            "y": 180
          }
        }
      },
      "eastwest": {
        "submodel": {
          "input": {
            "model": "lightningadditions:tube_horizontal_input",
            "y": 270
          },
          "output": {
            "model": "lightningadditions:tube_horizontal_output",
            "y": 270
          }
        }
      },
      "downwest": {
        "submodel": {
          "input": {
            "model": "lightningadditions:tube_bottom_input"
          },
          "output": {
            "model": "lightningadditions:tube_horizontal_output",
            "y": 270
          }
        }
      },
      "upwest": {
        "submodel": {
          "input": {
            "model": "lightningadditions:tube_top_input"
          },
          "output": {
            "model": "lightningadditions:tube_horizontal_output",
            "y": 270
          }
        }
      },
      "downeast": {
        "submodel": {
          "input": {
            "model": "lightningadditions:tube_bottom_input"
          },
          "output": {
            "model": "lightningadditions:tube_horizontal_output",
            "y": 90
          }
        }
      },
      "upeast": {
        "submodel": {
          "input": {
            "model": "lightningadditions:tube_top_input"
          },
          "output": {
            "model": "lightningadditions:tube_horizontal_output",
            "y": 90
          }
        }
      }
    }
  }
}